odoo9_addon_stock_scanner_shipping-9.0.1.0.0-py2.7-nspkg.pth
odoo_addons/stock_scanner_shipping/__openerp__.py
odoo_addons/stock_scanner_shipping/__init__.py
odoo_addons/stock_scanner_shipping/README.rst
odoo_addons/stock_scanner_shipping/data/Stock.scenario
odoo_addons/stock_scanner_shipping/data/Shipping/scanner_scenario_step_shipping_unknown_location.py
odoo_addons/stock_scanner_shipping/data/Shipping/scanner_scenario_step_shipping_location_selection.py
odoo_addons/stock_scanner_shipping/data/Shipping/scanner_scenario_step_shipping_product_selection.py
odoo_addons/stock_scanner_shipping/data/Shipping/scanner_scenario_step_shipping_unknown_picking.py
odoo_addons/stock_scanner_shipping/data/Shipping/scanner_scenario_step_shipping_quantity_selection.py
odoo_addons/stock_scanner_shipping/data/Shipping/scanner_scenario_step_shipping_invalid_quantity.py
odoo_addons/stock_scanner_shipping/data/Shipping/scanner_scenario_step_shipping_picking_selection.py
odoo_addons/stock_scanner_shipping/data/Shipping/Shipping.scenario
odoo_addons/stock_scanner_shipping/data/Shipping/scanner_scenario_step_shipping_invalid_product.py
odoo_addons/stock_scanner_shipping/data/Shipping/scanner_scenario_step_shipping_end_confirmation.py
odoo_addons/stock_scanner_shipping/data/Shipping/scanner_scenario_step_shipping_done.py
odoo_addons/stock_scanner_shipping/images/scenario.png
odoo9_addon_stock_scanner_shipping-9.0.1.0.0.dist-info/top_level.txt
odoo9_addon_stock_scanner_shipping-9.0.1.0.0.dist-info/WHEEL
odoo9_addon_stock_scanner_shipping-9.0.1.0.0.dist-info/RECORD
odoo9_addon_stock_scanner_shipping-9.0.1.0.0.dist-info/metadata.json
odoo9_addon_stock_scanner_shipping-9.0.1.0.0.dist-info/DESCRIPTION.rst
odoo9_addon_stock_scanner_shipping-9.0.1.0.0.dist-info/METADATA
odoo9_addon_stock_scanner_shipping-9.0.1.0.0.dist-info/namespace_packages.txt
